ipython_doctester
