Metadata-Version: 1.0
Name: ipython_doctester
Version: 0.3.0
Summary: Run doctests in individual IPython Notebook cells
Home-page: http://pypi.python.org/pypi/ipython_doctester/
Author: Catherine Devlin
Author-email: catherine.devlin@gmail.com
License: MIT
Platform: UNKNOWN
